sage_analysis/__init__.py
sage_analysis/__version__.py
sage_analysis/data_class.py
sage_analysis/default_analysis_arguments.py
sage_analysis/example_calcs.py
sage_analysis/example_plots.py
sage_analysis/galaxy_analysis.py
sage_analysis/model.py
sage_analysis/observations.py
sage_analysis/plot_helper.py
sage_analysis/sage_binary.py
sage_analysis/sage_hdf5.py
sage_analysis/utils.py
sage_analysis/tests/__init__.py
sage_analysis/tests/test_galaxy_analysis.py
sage_analysis/tests/test_galaxy_history.py
sage_analysis/tests/test_utils.py
sage_analysis-0.2.4.dist-info/LICENSE
sage_analysis-0.2.4.dist-info/METADATA
sage_analysis-0.2.4.dist-info/WHEEL
sage_analysis-0.2.4.dist-info/top_level.txt
sage_analysis-0.2.4.dist-info/RECORD
