Metadata-Version: 2.1
Name: sage-analysis
Version: 0.2.4
Summary: Ingests, analyses, and plots SAGE data products.
Home-page: https://github.com/sage-home/sage-analysis
Download-URL: https://pypi.org/project/sage-analysis
Author: Jacob Seiler
Author-email: jacob.seiler94@gmail.com
Project-URL: Documentation, https://sage-model.readthedocs.io
Project-URL: Source Code, https://github.com/sage-home/sage-analysis
Keywords: SAGE redshift astronomy astrophysics galaxy semi-analytic model
Classifier: Programming Language :: Python :: 3
Classifier: Programming Language :: Python :: 3.5
Classifier: Programming Language :: Python :: 3.6
Classifier: Programming Language :: Python :: 3.7
Classifier: License :: OSI Approved :: BSD License
Classifier: Operating System :: MacOS
Classifier: Operating System :: Unix
License-File: LICENSE
Requires-Dist: h5py >=2.9.0
Requires-Dist: matplotlib >=3.5.0
Requires-Dist: numpy >=1.15.4
Requires-Dist: scipy >=1.2.1
Requires-Dist: tqdm >=4.31.1
